dplutils/__init__.py
dplutils/_version.py
dplutils/cli.py
dplutils/util.py
dplutils/observer/__init__.py
dplutils/observer/aim.py
dplutils/observer/mlflow.py
dplutils/observer/ray.py
dplutils/pipeline/__init__.py
dplutils/pipeline/executor.py
dplutils/pipeline/graph.py
dplutils/pipeline/hyperqueue.py
dplutils/pipeline/ray.py
dplutils/pipeline/staging.py
dplutils/pipeline/stream.py
dplutils/pipeline/task.py
dplutils/pipeline/utils.py
dplutils/pipeline/xpy.py
dplutils-0.8.2.dist-info/licenses/LICENSE
dplutils-0.8.2.dist-info/METADATA
dplutils-0.8.2.dist-info/WHEEL
dplutils-0.8.2.dist-info/top_level.txt
dplutils-0.8.2.dist-info/RECORD
