Metadata-Version: 2.4
Name: dplutils
Version: 0.8.2
Author-email: Scientifc Software Engineering Center at JHU <ssec@jhu.edu>
License: BSD 3-Clause License
Project-URL: homepage, https://dplutils.readthedocs.io/en/latest
Project-URL: documentation, https://dplutils.readthedocs.io/en/latest
Project-URL: repository, https://github.com/ssec-jhu/dplutils
Requires-Python: <3.12,>=3.10
License-File: LICENSE
Requires-Dist: pandas
Requires-Dist: numpy
Requires-Dist: ray[data]>=2.10
Requires-Dist: pyarrow
Requires-Dist: networkx
Requires-Dist: cloudpickle
Provides-Extra: dev
Requires-Dist: bandit>=1.7; extra == "dev"
Requires-Dist: build; extra == "dev"
Requires-Dist: pytest; extra == "dev"
Requires-Dist: pytest-cov; extra == "dev"
Requires-Dist: ruff; extra == "dev"
Requires-Dist: tox; extra == "dev"
Provides-Extra: docs
Requires-Dist: sphinx; extra == "docs"
Requires-Dist: sphinx_book_theme; extra == "docs"
Requires-Dist: sphinx-automodapi; extra == "docs"
Requires-Dist: sphinx-issues; extra == "docs"
Requires-Dist: nbsphinx; extra == "docs"
Dynamic: license-file
